NetABM/ABM.py
NetABM/__init__.py
NetABM-0.0.3.dist-info/METADATA
NetABM-0.0.3.dist-info/WHEEL
NetABM-0.0.3.dist-info/top_level.txt
NetABM-0.0.3.dist-info/RECORD
