Metadata-Version: 2.1
Name: NetABM
Version: 0.0.3
Summary: Enabling different Network Configurations for ABM
Home-page: UNKNOWN
Author: Christoph Krueger
Author-email: <christoph.kruger@yahoo.com>
License: UNKNOWN
Keywords: python,ABM,Network,stochastic
Platform: UNKNOWN
Classifier: Development Status :: 1 - Planning
Classifier: Intended Audience :: Developers
Classifier: Programming Language :: Python :: 3
Classifier: Operating System :: Unix
Classifier: Operating System :: MacOS :: MacOS X
Classifier: Operating System :: Microsoft :: Windows
Requires-Dist: scipy
Requires-Dist: matplotlib
Requires-Dist: numpy
Requires-Dist: networkx
